pipen_lock.py
pipen_lock-1.1.0.dist-info/METADATA
pipen_lock-1.1.0.dist-info/WHEEL
pipen_lock-1.1.0.dist-info/entry_points.txt
pipen_lock-1.1.0.dist-info/licenses/LICENSE
pipen_lock-1.1.0.dist-info/RECORD
