Metadata-Version: 2.4
Name: pipen-lock
Version: 1.1.0
Summary: Process lock for pipen to prevent multiple runs at the same time
License: MIT
License-File: LICENSE
Author: pwwang
Author-email: pwwang@pwwang.com
Requires-Python: >=3.9,<4.0
Classifier: License :: OSI Approved :: MIT License
Classifier: Programming Language :: Python :: 3
Classifier: Programming Language :: Python :: 3.9
Classifier: Programming Language :: Python :: 3.10
Classifier: Programming Language :: Python :: 3.11
Classifier: Programming Language :: Python :: 3.12
Classifier: Programming Language :: Python :: 3.13
Classifier: Programming Language :: Python :: 3.14
Requires-Dist: filelock (>=3,<4)
Requires-Dist: pipen (==1.1.*)
